alto_anomaly_detection/__init__.py
alto_anomaly_detection-0.1.0.dist-info/WHEEL
alto_anomaly_detection-0.1.0.dist-info/METADATA
alto_anomaly_detection-0.1.0.dist-info/RECORD
