Metadata-Version: 2.1
Name: alto-anomaly-detection
Version: 0.1.0
Summary: 
Author: mcvoramet
Author-email: vc2543@gmail.com
Requires-Python: >=3.8,<4.0
Classifier: Programming Language :: Python :: 3
Classifier: Programming Language :: Python :: 3.8
Classifier: Programming Language :: Python :: 3.9
Classifier: Programming Language :: Python :: 3.10
Classifier: Programming Language :: Python :: 3.11
Requires-Dist: azure-cosmos (>=4.3.0,<5.0.0)
Requires-Dist: crate (>=0.27.2,<0.28.0)
Requires-Dist: numpy (>=1.23.4,<2.0.0)
Requires-Dist: pandas (>=1.5.0,<2.0.0)
Requires-Dist: pendulum (>=2.1.2,<3.0.0)
Requires-Dist: plotly (>=5.10.0,<6.0.0)
Requires-Dist: sklearn (>=0.0,<0.1)
Requires-Dist: tqdm (>=4.64.1,<5.0.0)
